tinyface/__init__.py
tinyface/cli/__init__.py
tinyface/cli/commands/__init__.py
tinyface/cli/commands/swap.py
tinyface/cli/filesystem.py
tinyface/cli/image.py
tinyface/cli/tasks.py
tinyface/cli/version.py
tinyface/config.py
tinyface/core/__init__.py
tinyface/core/detector.py
tinyface/core/embedder.py
tinyface/core/enhancer.py
tinyface/core/swapper.py
tinyface/download.py
tinyface/inference.py
tinyface/typing.py
tinyface/utils.py
tinyface-1.0.1.dist-info/LICENSE
tinyface-1.0.1.dist-info/METADATA
tinyface-1.0.1.dist-info/WHEEL
tinyface-1.0.1.dist-info/entry_points.txt
tinyface-1.0.1.dist-info/RECORD
