Metadata-Version: 2.1
Name: tinyface
Version: 1.0.1
Summary: The minimalist face swapping tool that just works.
Home-page: https://del.wang
License: MIT
Keywords: ai,face swap,facefusion,insightface
Author: Del Wang
Author-email: hello@xbox.work
Maintainer: Del Wang
Maintainer-email: hello@xbox.work
Requires-Python: >=3.10,<4.0
Classifier: License :: OSI Approved :: MIT License
Classifier: Programming Language :: Python :: 3
Classifier: Programming Language :: Python :: 3.10
Classifier: Programming Language :: Python :: 3.11
Classifier: Programming Language :: Python :: 3.12
Classifier: Programming Language :: Python :: 3.13
Requires-Dist: async-tasks-python (>=1.0.0,<2.0.0)
Requires-Dist: filetype (>=1.2.0,<2.0.0)
Requires-Dist: numpy (>=2.1.2,<3.0.0)
Requires-Dist: onnx (>=1.17.0,<2.0.0)
Requires-Dist: onnxruntime (>=1.20.0,<2.0.0)
Requires-Dist: opencv-python (>=4.10.0.84,<5.0.0.0)
Requires-Dist: pooch (>=1.8.2,<2.0.0)
Requires-Dist: tqdm (>=4.67.0,<5.0.0)
Project-URL: Changelog, https://github.com/idootop/TinyFace/blob/main/CHANGELOG.md
Project-URL: Documentation, https://github.com/idootop/TinyFace/README.md
Project-URL: Repository, https://github.com/idootop/TinyFace
